napistu_torch/__init__.py
napistu_torch/__main__.py
napistu_torch/_cli.py
napistu_torch/configs.py
napistu_torch/constants.py
napistu_torch/napistu_data.py
napistu_torch/napistu_data_store.py
napistu_torch/vertex_tensor.py
napistu_torch/data/__init__.py
napistu_torch/data/compare_napistu_data.py
napistu_torch/data/constants.py
napistu_torch/data/data_utils.py
napistu_torch/data/dataset.py
napistu_torch/evaluation/__init__.py
napistu_torch/evaluation/constants.py
napistu_torch/evaluation/edge_prediction.py
napistu_torch/evaluation/edge_weights.py
napistu_torch/evaluation/manager.py
napistu_torch/evaluation/model_comparison.py
napistu_torch/evaluation/pathways.py
napistu_torch/evaluation/relation_prediction.py
napistu_torch/labels/__init__.py
napistu_torch/labels/apply.py
napistu_torch/labels/constants.py
napistu_torch/labels/create.py
napistu_torch/labels/labeling_manager.py
napistu_torch/lightning/__init__.py
napistu_torch/lightning/callbacks.py
napistu_torch/lightning/constants.py
napistu_torch/lightning/datamodule.py
napistu_torch/lightning/edge_batch_datamodule.py
napistu_torch/lightning/full_graph_datamodule.py
napistu_torch/lightning/tasks.py
napistu_torch/lightning/trainer.py
napistu_torch/lightning/workflows.py
napistu_torch/load/__init__.py
napistu_torch/load/artifacts.py
napistu_torch/load/checkpoints.py
napistu_torch/load/constants.py
napistu_torch/load/encoders.py
napistu_torch/load/encoding.py
napistu_torch/load/encoding_manager.py
napistu_torch/load/foundation_model_etl.py
napistu_torch/load/foundation_models.py
napistu_torch/load/gcs.py
napistu_torch/load/napistu_graphs.py
napistu_torch/load/stratification.py
napistu_torch/ml/__init__.py
napistu_torch/ml/constants.py
napistu_torch/ml/hugging_face.py
napistu_torch/ml/losses.py
napistu_torch/ml/metrics.py
napistu_torch/ml/splitting.py
napistu_torch/ml/wandb.py
napistu_torch/models/__init__.py
napistu_torch/models/constants.py
napistu_torch/models/edge_encoder.py
napistu_torch/models/head_utils.py
napistu_torch-0.3.9.dist-info/licenses/LICENSE
napistu_torch-0.3.9.dist-info/METADATA
napistu_torch-0.3.9.dist-info/WHEEL
napistu_torch-0.3.9.dist-info/entry_points.txt
napistu_torch-0.3.9.dist-info/top_level.txt
napistu_torch-0.3.9.dist-info/RECORD
