Metadata-Version: 2.4
Name: napistu-torch
Version: 0.3.9
Summary: PyTorch-based toolkit for working with Napistu network graphs
Home-page: https://github.com/napistu/napistu-torch
Author: Sean Hackett
Author-email: seanmchackett@gmail.com
Classifier: License :: OSI Approved :: MIT License
Classifier: Operating System :: OS Independent
Classifier: Programming Language :: Python :: 3
Classifier: Programming Language :: Python :: 3 :: Only
Classifier: Programming Language :: Python :: 3.11
Requires-Python: >=3.11
License-File: LICENSE
Requires-Dist: click<9.0.0,>=8.1.0
Requires-Dist: torch>=2.0.0
Requires-Dist: napistu>=0.8.0
Requires-Dist: numpy>=1.20.0
Requires-Dist: pandas>=1.3.0
Requires-Dist: pydantic>=2.0.0
Requires-Dist: rich<14.0.0,>=13.0.0
Requires-Dist: scikit-learn>=1.0.0
Provides-Extra: pyg
Requires-Dist: torch-geometric>=2.4.0; extra == "pyg"
Requires-Dist: torch-sparse>=0.6.17; extra == "pyg"
Requires-Dist: torch-scatter>=2.1.1; extra == "pyg"
Provides-Extra: dev
Requires-Dist: black>=22.0.0; extra == "dev"
Requires-Dist: huggingface_hub>=1.2.1; extra == "dev"
Requires-Dist: lightning; extra == "dev"
Requires-Dist: pytest>=7.0.0; extra == "dev"
Requires-Dist: ruff>=0.1.0; extra == "dev"
Requires-Dist: seaborn>=0.13.0; extra == "dev"
Requires-Dist: torch-geometric>=2.4.0; extra == "dev"
Requires-Dist: torch-sparse>=0.6.17; extra == "dev"
Requires-Dist: torch-scatter>=2.1.1; extra == "dev"
Requires-Dist: wandb; extra == "dev"
Provides-Extra: lightning
Requires-Dist: huggingface_hub>=0.20.0; extra == "lightning"
Requires-Dist: lightning; extra == "lightning"
Requires-Dist: tqdm>=4.65.0; extra == "lightning"
Requires-Dist: wandb; extra == "lightning"
Provides-Extra: analysis
Requires-Dist: seaborn>=0.13.0; extra == "analysis"
Dynamic: license-file
